respeaker/__init__.py
respeaker/bing_speech_api.py
respeaker/fft.py
respeaker/gpio.py
respeaker/microphone.py
respeaker/pixel_ring.py
respeaker/player.py
respeaker/spectrum_analyzer.py
respeaker/spi.py
respeaker/vad.py
respeaker/pocketsphinx-data/dictionary.txt
respeaker/pocketsphinx-data/keywords.txt
respeaker/pocketsphinx-data/hmm/feat.params
respeaker/pocketsphinx-data/hmm/mdef
respeaker/pocketsphinx-data/hmm/means
respeaker/pocketsphinx-data/hmm/noisedict
respeaker/pocketsphinx-data/hmm/sendump
respeaker/pocketsphinx-data/hmm/transition_matrices
respeaker/pocketsphinx-data/hmm/variances
respeaker/usb_hid/__init__.py
respeaker/usb_hid/hidapi_backend.py
respeaker/usb_hid/interface.py
respeaker/usb_hid/pyusb_backend.py
respeaker/usb_hid/pywinusb_backend.py
snips_respeaker-0.6.2.dist-info/DESCRIPTION.rst
snips_respeaker-0.6.2.dist-info/METADATA
snips_respeaker-0.6.2.dist-info/RECORD
snips_respeaker-0.6.2.dist-info/WHEEL
snips_respeaker-0.6.2.dist-info/entry_points.txt
snips_respeaker-0.6.2.dist-info/metadata.json
snips_respeaker-0.6.2.dist-info/top_level.txt
