Metadata-Version: 2.0
Name: snips-respeaker
Version: 0.6.2
Summary: To build voice enabled objects with ReSpeaker
Home-page: https://github.com/snipsco/respeaker_python_library
Author: Yihui Xiong
Author-email: yihui.xiong@seeed.cc
License: Apache 2.0
Keywords: audio,respeaker,keyword spotting,pocketsphinx,voice activity detection
Platform: UNKNOWN
Classifier: Development Status :: 4 - Beta
Classifier: Intended Audience :: Developers
Classifier: Topic :: Software Development :: Build Tools
Classifier: License :: OSI Approved :: Apache Software License
Requires-Dist: hidapi
Requires-Dist: pyaudio
Requires-Dist: requests
Requires-Dist: webrtcvad
